README.md
setup.py
hotdog/__init__.py
hotdog/indexer.py
steem_hotdog.egg-info/PKG-INFO
steem_hotdog.egg-info/SOURCES.txt
steem_hotdog.egg-info/dependency_links.txt
steem_hotdog.egg-info/entry_points.txt
steem_hotdog.egg-info/requires.txt
steem_hotdog.egg-info/top_level.txt